kb_distributions/Binomialdistribution.py
kb_distributions/Gaussiandistribution.py
kb_distributions/Generaldistribution.py
kb_distributions/__init__.py
kb_distributions-0.1.dist-info/DESCRIPTION.rst
kb_distributions-0.1.dist-info/METADATA
kb_distributions-0.1.dist-info/RECORD
kb_distributions-0.1.dist-info/WHEEL
kb_distributions-0.1.dist-info/metadata.json
kb_distributions-0.1.dist-info/top_level.txt
